{
  "description": "项目私有配置文件。此文件中的内容将覆盖 project.config.json 中的相同字段。项目的改动优先同步到此文件中。详见文档：https://developers.weixin.qq.com/miniprogram/dev/devtools/projectconfig.html",
  "projectname": "ElectricityPaymentSystem",
  "setting": {
    "compileHotReLoad": true,
    "urlCheck": false,
    "es6": true,
    "enhance": true,
    "postcss": true,
    "preloadBackgroundData": false,
    "minified": true,
    "newFeature": false,
    "coverView": true,
    "nodeModules": false,
    "autoAudits": false,
    "showShadowRootInWxmlPanel": true,
    "scopeDataCheck": false,
    "uglifyFileName": false,
    "checkInvalidKey": true,
    "checkSiteMap": false,
    "uploadWithSourceMap": true,
    "lazyloadPlaceholderEnable": false,
    "useMultiFrameRuntime": true,
    "useApiHook": true,
    "useApiHostProcess": true,
    "babelSetting": {
      "ignore": [],
      "disablePlugins": [],
      "outputPath": ""
    },
    "enableEngineNative": false,
    "useIsolateContext": false,
    "userConfirmedBundleSwitch": false,
    "packNpmManually": false,
    "packNpmRelationList": [],
    "minifyWXSS": true,
    "disableUseStrict": false,
    "minifyWXML": true,
    "showES6CompileOption": false,
    "useCompilerPlugins": false,
    "ignoreUploadUnusedFiles": true,
    "skylineRenderEnable": false,
    "useStaticServer": false,
    "useLanDebug": false,
    "ignoreDevUnusedFiles": true,
    "bigPackageSizeSupport": false
  },
  "condition": {},
  "libVersion": "3.8.11"
}